{
  "books": [
    {
      "title": "learn html",
      "price": "51",
      "description": "ninio",
      "id": "24c6d199-69a9-40e7-9b85-cc3c5608c63f"
    },
    {
      "title": "learn css",
      "price": "95",
      "description": "fewoijfio",
      "id": "a7391c67-cfa9-44e4-ade1-5d2018f5f339"
    },
    {
      "title": "learn javascript",
      "price": "+5+",
      "description": "oipjoih",
      "id": "59d47f03-d6de-4d21-ad3a-9cbf8191042a"
    },
    {
      "title": "demo",
      "price": "3242",
      "description": "pofmepof",
      "id": "629e408a-5610-4a69-ab4b-2b965a7dbefa"
    }
  ]
}